google_artifactregistry_auth/tox_bootstrap.py
keyrings/gauth.py
tests/tox-plugin/setup.py
tests/tox-plugin/tox.ini
keyrings.google_artifactregistry_auth-1.1.2.dist-info/LICENSE
keyrings.google_artifactregistry_auth-1.1.2.dist-info/METADATA
keyrings.google_artifactregistry_auth-1.1.2.dist-info/WHEEL
keyrings.google_artifactregistry_auth-1.1.2.dist-info/entry_points.txt
keyrings.google_artifactregistry_auth-1.1.2.dist-info/top_level.txt
keyrings.google_artifactregistry_auth-1.1.2.dist-info/RECORD
