Metadata-Version: 2.1
Name: keyrings.google-artifactregistry-auth
Version: 1.1.2
Summary: Keyring backend for Google Auth tokens
Home-page: https://github.com/GoogleCloudPlatform/artifact-registry-python-tools
Author: Megan Kuo
Author-email: megankuo@google.com
Classifier: Development Status :: 5 - Production/Stable
Classifier: Intended Audience :: Developers
Classifier: License :: OSI Approved :: Apache Software License
Classifier: Programming Language :: Python :: 3
Classifier: Programming Language :: Python :: 3 :: Only
Requires-Python: >=3.6
Provides-Extra: testing
Provides-Extra: tox
License-File: LICENSE
